srx_lib_docs/__init__.py
srx_lib_docs/convert.py
srx_lib_docs/markdown.py
srx_lib_docs/pipeline.py
srx_lib_docs-0.1.7.dist-info/METADATA
srx_lib_docs-0.1.7.dist-info/WHEEL
srx_lib_docs-0.1.7.dist-info/RECORD
