Metadata-Version: 2.4
Name: srx-lib-docs
Version: 0.1.7
Summary: Document utilities for SRX: extract text from PDF, DOCX, PPTX, XLSX, and audio files (MP3, M4A, WAV)
Author-email: SRX <dev@srx.id>
Requires-Python: >=3.12
Requires-Dist: aiofiles>=23.2.1
Requires-Dist: httpx>=0.28.1
Requires-Dist: markitdown[all]>=0.1.3
Requires-Dist: openpyxl>=3.1.2
Requires-Dist: pillow>=10.0.0
Requires-Dist: pypdf2>=3.0.1
Requires-Dist: python-docx>=0.8.11
Requires-Dist: python-pptx>=0.6.21
